[
  {
    "id": 1,
    "title": "Yaklabs IoT Platform",
    "description": "Innovative platform for IoT device management and data analytics with real-time capabilities.",
    "icon": "fas fa-flask",
    "technologies": [
      "Full-Stack Developer",
      "iOT Backend",
      "AI/ML"
    ],
    "url": "https://github.com/W-Mirshod/yaklabs-platform"
  },
  {
    "id": 2,
    "title": "Taffi",
    "description": "Professional project developed for Taffi company.",
    "icon": "fas fa-code",
    "technologies": [
      "CTO",
      "AI Computer Vision",
      "Backend API",
      "B2B SaaS"
    ],
    "url": "#"
  }
]